postgres_insert_csv_operator/__init__.py
postgres_insert_csv_operator/postgres_insert_csv_operator.py
amsterdam_airflow_postgres_insert_csv_operator-1.1.dist-info/WHEEL
amsterdam_airflow_postgres_insert_csv_operator-1.1.dist-info/METADATA
amsterdam_airflow_postgres_insert_csv_operator-1.1.dist-info/RECORD
